gryml/__init__.py
gryml/cli.py
gryml/core.py
gryml/pipes.py
gryml/strategies.py
gryml/utils.py
gryml-0.202002.2a616.dist-info/METADATA
gryml-0.202002.2a616.dist-info/WHEEL
gryml-0.202002.2a616.dist-info/entry_points.txt
gryml-0.202002.2a616.dist-info/top_level.txt
gryml-0.202002.2a616.dist-info/RECORD
