Metadata-Version: 2.1
Name: gryml
Version: 0.202002.2a616
Summary: Gryml YAML Processor
Home-page: https://github.com/achichenin/gryml
Author: Alexander Chichenin
Author-email: admin@somebugs.com
License: UNKNOWN
Keywords: yaml helm chart k8s kubernetes
Platform: UNKNOWN
Classifier: Development Status :: 3 - Alpha
Classifier: Intended Audience :: Developers
Classifier: Topic :: Software Development :: Build Tools
Classifier: Programming Language :: Python :: 3
Classifier: License :: OSI Approved :: MIT License
Classifier: Operating System :: OS Independent
Requires-Python: >=3.7
Requires-Dist: ruamel.yaml (>=0.16.5)
Requires-Dist: jinja2 (>=2.10.3)
Requires-Dist: colorlog (>=4.1.0)
